zero_sdk/__init__.py
zero_sdk/zero.py
zero_sdk-0.1.10.dist-info/LICENSE
zero_sdk-0.1.10.dist-info/WHEEL
zero_sdk-0.1.10.dist-info/METADATA
zero_sdk-0.1.10.dist-info/RECORD
